ezblock_real/__init__.py
ezblock_real/modules.py
ezblockreal/__init__.py
ezblockreal/modules.py
ezblockreal-0.1.4.dist-info/METADATA
ezblockreal-0.1.4.dist-info/WHEEL
ezblockreal-0.1.4.dist-info/top_level.txt
ezblockreal-0.1.4.dist-info/RECORD
