Metadata-Version: 2.1
Name: ezblockreal
Version: 0.1.4
Summary: Sunfounder utility block to use real components
Home-page: https://github.com/gpspelle/ezblock-real-modules/
Author: gpspelle
Author-email: gpsunicamp016@gmail.com
License: MIT
Keywords: Raspberrypi,Sunfounder,Ezblock
Platform: UNKNOWN
